README.md
setup.cfg
setup.py
sallfus/__init__.py
sallfus/comparison.py
sallfus/measures.py
sallfus.egg-info/PKG-INFO
sallfus.egg-info/SOURCES.txt
sallfus.egg-info/dependency_links.txt
sallfus.egg-info/top_level.txt
sallfus/fusion/atrousCPU.py
sallfus/fusion/atrousGPU.py
sallfus/fusion/broveyCPU.py
sallfus/fusion/broveyGPU.py
sallfus/fusion/multiplicativeCPU.py
sallfus/fusion/multiplicativeGPU.py
sallfus/fusion/pcaCPU.py
sallfus/fusion/pcaGPU.py