Metadata-Version: 1.1
Name: sallfus
Version: 0.1
Summary: Specialized library to carry out the fusion of satellite images using different techniques.
Home-page: https://github.com/Parall-UD/sallfus
Author: Parall UD
Author-email: parallud2019@gmail.com
License: LGPL v3
Download-URL: https://github.com/Parall-UD/sallfus/blob/master/dist/sallfus-0.1.tar.gz
Keywords: fusion,cuda,images,Satellite,quality
Platform: UNKNOWN
Classifier: Programming Language :: Python
Classifier: Programming Language :: Python :: 3.6
